beit3/__init__.py
beit3/datasets.py
beit3/engine_for_finetuning.py
beit3/glossary.py
beit3/modeling_finetune.py
beit3/modeling_utils.py
beit3/optim_factory.py
beit3/randaug.py
beit3/run_beit3_finetuning.py
beit3/utils.py
beit3_gml-0.1.3.dist-info/LICENSE
beit3_gml-0.1.3.dist-info/METADATA
beit3_gml-0.1.3.dist-info/NOTICE.md
beit3_gml-0.1.3.dist-info/WHEEL
beit3_gml-0.1.3.dist-info/top_level.txt
beit3_gml-0.1.3.dist-info/RECORD
