Metadata-Version: 2.1
Name: beit3-gml
Version: 0.1.3
Summary: Package for beit3, part of UniLM by Microsoft, customized for GML tasks
Home-page: https://github.com/gimletlabs/unilm
Author: Gimlet Labs
License: MIT
Classifier: Programming Language :: Python :: 3
Classifier: License :: OSI Approved :: MIT License
Classifier: Operating System :: OS Independent
Requires-Python: >=3.8
License-File: LICENSE
License-File: NOTICE.md
Requires-Dist: torch
Requires-Dist: torchvision
Requires-Dist: timm
Requires-Dist: Pillow
Requires-Dist: blobfile
Requires-Dist: mypy
Requires-Dist: numpy
Requires-Dist: pytest
Requires-Dist: requests
Requires-Dist: einops
Requires-Dist: scipy
Requires-Dist: ftfy
Requires-Dist: opencv-python-headless
Requires-Dist: sentencepiece
Requires-Dist: pyarrow
Requires-Dist: transformers
Requires-Dist: pycocotools
Requires-Dist: pycocoevalcap
Requires-Dist: torchscale-gml
